fitdata/__init__.py
fitdata/basic_calc.py
fitdata/errors.py
fitdata/fitdata.py
fitdata/interfaces.py
fitdata/objective.py
fitdata/other_calc.py
fitdata/weeklyprogression.py
fitdata-1.5.0.dist-info/METADATA
fitdata-1.5.0.dist-info/WHEEL
fitdata-1.5.0.dist-info/top_level.txt
fitdata-1.5.0.dist-info/RECORD
