Metadata-Version: 2.2
Name: fitdata
Version: 1.5.0
Summary: A Python package for managing fitness-related data and goals.
Home-page: https://gitlab.com/misternobody01/fitdata.git
Author: Monsieur Nobody
Author-email: monsieurnobody01@gmail.com
License: MIT
Keywords: fitness health bmi bmr tdee macros python
Classifier: Programming Language :: Python :: 3
Classifier: License :: OSI Approved :: MIT License
Classifier: Operating System :: OS Independent
Classifier: Intended Audience :: Developers
Classifier: Topic :: Software Development :: Libraries :: Python Modules
Requires-Python: >=3.6
Requires-Dist: numpy>=1.21.0
Requires-Dist: pandas>=1.3.0
Dynamic: author
Dynamic: author-email
Dynamic: classifier
Dynamic: description
Dynamic: description-content-type
Dynamic: home-page
Dynamic: keywords
Dynamic: license
Dynamic: requires-dist
Dynamic: requires-python
Dynamic: summary
